fatalctrl/__init__.py
fatalctrl/features.py
fatalctrl/key_listen.py
fatalctrl/main.py
fatal_ctrl-0.0.1.dist-info/LICENSE
fatal_ctrl-0.0.1.dist-info/METADATA
fatal_ctrl-0.0.1.dist-info/WHEEL
fatal_ctrl-0.0.1.dist-info/top_level.txt
fatal_ctrl-0.0.1.dist-info/RECORD
